GaussNBO/__init__.py
GaussNBO/app.py
GaussNBO/config/__init__.py
GaussNBO/config/constants.py
GaussNBO/docs/__init__.py
GaussNBO/docs/nbo_analysis.py
GaussNBO/docs/nbo_parser.py
GaussNBO/parsers/__init__.py
GaussNBO/parsers/parser_directionality.py
GaussNBO/parsers/parser_natural_atomic_orbital_occupancies.py
GaussNBO/parsers/parser_natural_orbital_analysis.py
GaussNBO/parsers/parser_natural_population_analysis.py
GaussNBO/parsers/parser_nbo_summary.py
GaussNBO/parsers/parser_occupacy.py
GaussNBO/parsers/parser_second_order_perturbation.py
GaussNBO/templates/BOND_ORBITAL_COEFFICIENTS_HYBRIDS.html
GaussNBO/templates/NATURAL_ATOMIC_ORBITAL_ACCUPACIES.html
GaussNBO/templates/NATURAL_BOND_ORBITALS_SUMMARY.html
GaussNBO/templates/NATURAL_BOND_ORBITAL_ANALYSIS.html
GaussNBO/templates/NHO_DIRECTIONALITY_BOND_BENDING.html
GaussNBO/templates/SECOND_ORDER_PERTURBATION_THEORY_ANALYSIS.html
GaussNBO/templates/SUMMARY_OF_NATURAL_POPULATION_ANALYSIS.html
GaussNBO/templates/nbo.html
GaussNBO/utils/__init__.py
gaussnbo-0.1.0.dist-info/licenses/LICENSE
gaussnbo-0.1.0.dist-info/METADATA
gaussnbo-0.1.0.dist-info/WHEEL
gaussnbo-0.1.0.dist-info/top_level.txt
gaussnbo-0.1.0.dist-info/RECORD
