Metadata-Version: 2.4
Name: GaussNBO
Version: 0.1.0
Summary: GaussNBO is a Python package for parsing Natural Bond Orbital (NBO) data from Gaussian log files.
Author: Sina Gilassi
Author-email: <sina.gilassi@gmail.com>
License: MIT
Keywords: Python,Gaussian Software,Computational Chemistry,NBO,Natural Bond Orbital,NBO Parser
Classifier: Development Status :: 1 - Planning
Classifier: Intended Audience :: Education
Classifier: Programming Language :: Python :: 3
Classifier: Operating System :: Unix
Classifier: Operating System :: MacOS :: MacOS X
Classifier: Operating System :: Microsoft :: Windows
Requires-Python: >=3.10
License-File: LICENSE
Requires-Dist: jinja2
Dynamic: author
Dynamic: author-email
Dynamic: classifier
Dynamic: description
Dynamic: description-content-type
Dynamic: keywords
Dynamic: license
Dynamic: license-file
Dynamic: requires-dist
Dynamic: requires-python
Dynamic: summary
